annnet/__init__.py
annnet/_metadata.py
annnet/_version.py
annnet/adapters/__init__.py
annnet/adapters/_base.py
annnet/adapters/_proxy.py
annnet/adapters/_utils.py
annnet/adapters/graphtool_adapter.py
annnet/adapters/igraph_adapter.py
annnet/adapters/manager.py
annnet/adapters/networkx_adapter.py
annnet/adapters/pyg_adapter.py
annnet/algorithms/__init__.py
annnet/algorithms/traversal.py
annnet/core/_Annotation.py
annnet/core/_BulkOps.py
annnet/core/_Cache.py
annnet/core/_History.py
annnet/core/_Index.py
annnet/core/_Layers.py
annnet/core/_Slices.py
annnet/core/_Views.py
annnet/core/__init__.py
annnet/core/_helpers.py
annnet/core/graph.py
annnet/core/lazy_proxies/__init__.py
annnet/core/lazy_proxies/_generate_gt_proxy.py
annnet/core/lazy_proxies/_generate_nx_proxy.py
annnet/core/lazy_proxies/gt_lazyproxy.py
annnet/core/lazy_proxies/ig_lazyproxy.py
annnet/core/lazy_proxies/nx_lazyproxy.py
annnet/io/GraphDir_Parquet_io.py
annnet/io/GraphML_io.py
annnet/io/SBML_io.py
annnet/io/SIF_io.py
annnet/io/__init__.py
annnet/io/_utils.py
annnet/io/csv.py
annnet/io/cx2_io.py
annnet/io/dataframe_io.py
annnet/io/excel.py
annnet/io/io_annnet.py
annnet/io/json_io.py
annnet/io/registry.py
annnet/io/sbml_cobra_io.py
annnet/utils/config.py
annnet/utils/plotting.py
annnet/utils/typing.py
annnet/utils/validation.py
annnet-0.1.0.dist-info/METADATA
annnet-0.1.0.dist-info/WHEEL
annnet-0.1.0.dist-info/entry_points.txt
annnet-0.1.0.dist-info/licenses/LICENSE
annnet-0.1.0.dist-info/RECORD
