Metadata-Version: 2.4
Name: annnet
Version: 0.1.0
Summary: A Python tool to build, manipulate, and interoperate with flexible graph structures
Project-URL: Documentation, https://annnet.readthedocs.io/
Project-URL: Homepage, https://github.com/saezlab/annnet
Project-URL: Issues, https://github.com/saezlab/annnet/issues
Project-URL: Repository, https://github.com/saezlab/annnet
Author-email: Youssef Zerta <youssef.zerta@biomedtech.ueuromed.org>, Bottazzi Daniele <daniele.bottazzi@mail.polimi.it>, Denes Turei <turei.denes@gmail.com>
Maintainer-email: Bottazzi Daniele <daniele.bottazzi@mail.polimi.it>, Youssef Zerta <youssef.zerta@biomedtech.ueuromed.org>
License-Expression: BSD-3-Clause
License-File: LICENSE
Classifier: Development Status :: 3 - Alpha
Classifier: Intended Audience :: Developers
Classifier: Intended Audience :: Science/Research
Classifier: License :: OSI Approved :: BSD License
Classifier: Operating System :: OS Independent
Classifier: Programming Language :: Python :: 3
Classifier: Topic :: Scientific/Engineering :: Bio-Informatics
Classifier: Topic :: Scientific/Engineering :: Mathematics
Classifier: Topic :: Software Development :: Libraries :: Python Modules
Requires-Python: >=3.10
Requires-Dist: numpy>=1.24
Requires-Dist: polars>=0.20.0
Requires-Dist: scipy>=1.10
Provides-Extra: all
Requires-Dist: cobra>=0.26; extra == 'all'
Requires-Dist: graphviz; extra == 'all'
Requires-Dist: lxml>=4.9; extra == 'all'
Requires-Dist: matplotlib>=3.5; extra == 'all'
Requires-Dist: narwhals>=1.9; extra == 'all'
Requires-Dist: networkx>=3.3; extra == 'all'
Requires-Dist: numcodecs>=0.12; extra == 'all'
Requires-Dist: openpyxl>=3.1; extra == 'all'
Requires-Dist: pandas>=1.5; extra == 'all'
Requires-Dist: pyarrow>=10; extra == 'all'
Requires-Dist: pydot; extra == 'all'
Requires-Dist: python-igraph>=0.11; extra == 'all'
Requires-Dist: toml>=0.10; extra == 'all'
Requires-Dist: zarr>=2.18; extra == 'all'
Provides-Extra: backends
Requires-Dist: networkx>=3.3; extra == 'backends'
Requires-Dist: python-igraph>=0.11; extra == 'backends'
Provides-Extra: bio
Requires-Dist: cobra>=0.26; extra == 'bio'
Requires-Dist: lxml>=4.9; extra == 'bio'
Provides-Extra: dev
Requires-Dist: build>=1.2; extra == 'dev'
Requires-Dist: mypy>=1.10; extra == 'dev'
Requires-Dist: pytest-cov>=5.0; extra == 'dev'
Requires-Dist: pytest>=8.0; extra == 'dev'
Requires-Dist: ruff>=0.6; extra == 'dev'
Requires-Dist: twine>=5.0; extra == 'dev'
Provides-Extra: docs
Requires-Dist: mkdocs-jupyter>=0.25; extra == 'docs'
Requires-Dist: mkdocs-material>=9.5; extra == 'docs'
Requires-Dist: mkdocs>=1.6; extra == 'docs'
Requires-Dist: mkdocstrings[python]>=0.25; extra == 'docs'
Provides-Extra: excel
Requires-Dist: openpyxl>=3.1; extra == 'excel'
Provides-Extra: igraph
Requires-Dist: python-igraph>=0.11; extra == 'igraph'
Provides-Extra: io
Requires-Dist: lxml>=4.9; extra == 'io'
Requires-Dist: narwhals>=1.9; extra == 'io'
Requires-Dist: numcodecs>=0.12; extra == 'io'
Requires-Dist: pandas>=2.0; extra == 'io'
Requires-Dist: pyarrow>=10; extra == 'io'
Requires-Dist: toml>=0.10; extra == 'io'
Requires-Dist: zarr>=2.18; extra == 'io'
Provides-Extra: matplotlib
Requires-Dist: matplotlib>=3.5; extra == 'matplotlib'
Provides-Extra: networkx
Requires-Dist: networkx>=3.3; extra == 'networkx'
Provides-Extra: pandas
Requires-Dist: pandas>=1.5; extra == 'pandas'
Provides-Extra: parquet
Requires-Dist: pyarrow>=10; extra == 'parquet'
Provides-Extra: plot
Requires-Dist: graphviz; extra == 'plot'
Requires-Dist: matplotlib>=3.5; extra == 'plot'
Requires-Dist: pydot; extra == 'plot'
Provides-Extra: sbml
Requires-Dist: lxml>=4.9; extra == 'sbml'
Provides-Extra: storage
Requires-Dist: numcodecs>=0.12; extra == 'storage'
Requires-Dist: pandas>=2.0; extra == 'storage'
Requires-Dist: pyarrow>=10; extra == 'storage'
Requires-Dist: zarr>=2.18; extra == 'storage'
Provides-Extra: tests
Requires-Dist: codecov-cli>=10.2.0; extra == 'tests'
Requires-Dist: coverage>=6.0; extra == 'tests'
Requires-Dist: diff-cover; extra == 'tests'
Requires-Dist: narwhals>=1.9; extra == 'tests'
Requires-Dist: tox-gh>=1.5.0; extra == 'tests'
Requires-Dist: tox>=4.11; extra == 'tests'
Provides-Extra: zarr-io
Requires-Dist: numcodecs>=0.12; extra == 'zarr-io'
Requires-Dist: zarr>=2.18; extra == 'zarr-io'
